application/__init__.py
application/app.py
database/__init__.py
database/firebase.py
2023_assignemt1_viewscounter-0.1.0.dist-info/LICENSE
2023_assignemt1_viewscounter-0.1.0.dist-info/METADATA
2023_assignemt1_viewscounter-0.1.0.dist-info/WHEEL
2023_assignemt1_viewscounter-0.1.0.dist-info/top_level.txt
2023_assignemt1_viewscounter-0.1.0.dist-info/RECORD
