Metadata-Version: 2.1
Name: 2023-assignemt1-viewscounter
Version: 0.1.0
Summary: Questo assignment si concentra sulla creazione di un'applicazione che conta e monitora le visualizzazioni degli utenti
Author: Team CED
Author-email: damianoficara@gmail.com,c.ricci19@campus.unimib.it,emiliotoli21@gmail.com
License: MIT
License-File: LICENSE
